audio_sleuth/__init__.py
audio_sleuth/augmentations.py
audio_sleuth/detection_models.py
audio_sleuth/losses.py
audio_sleuth/trainer.py
audio_sleuth/data/__init__.py
audio_sleuth/data/collate.py
audio_sleuth/data/datasets.py
audio_sleuth/data/utils.py
tests/__init__.py
tests/test_resample.py
audio_sleuth-0.0.2.dist-info/LICENSE
audio_sleuth-0.0.2.dist-info/METADATA
audio_sleuth-0.0.2.dist-info/WHEEL
audio_sleuth-0.0.2.dist-info/top_level.txt
audio_sleuth-0.0.2.dist-info/RECORD
